prob_dim_red/__init__.py
prob_dim_red/__main__.py
prob_dim_red/_cli.py
prob_dim_red/dev.py
prob_dim_red/linear_gaussian_ppca.py
prob_dim_red/utils.py
prob_dim_red-0.0.3.dist-info/LICENSE
prob_dim_red-0.0.3.dist-info/METADATA
prob_dim_red-0.0.3.dist-info/WHEEL
prob_dim_red-0.0.3.dist-info/entry_points.txt
prob_dim_red-0.0.3.dist-info/top_level.txt
prob_dim_red-0.0.3.dist-info/RECORD
