Metadata-Version: 2.1
Name: prob_dim_red
Version: 0.0.3
Summary: Probabilistic dimensionality reduction methods
Author-email: François Victor <francois.victor@inrae.fr>, Jean-Benoist Leger <jbleger@hds.utc.fr>, Julien Chiquet <julien.chiquet@inrae.fr>
Maintainer-email: François Victor <francois.victor@inrae.fr>
License: MIT License
Project-URL: homepage, https://forgemia.inra.fr/mia-paris/reduction-dimension/prob_dim_red
Project-URL: repository, https://forgemia.inra.fr/mia-paris/reduction-dimension/prob_dim_red
Keywords: statistics,machine learning,dimensionality reduction,PCA
Classifier: License :: OSI Approved :: MIT License
Classifier: Development Status :: 2 - Pre-Alpha
Classifier: Programming Language :: Python
Classifier: Intended Audience :: Science/Research
Classifier: Topic :: Scientific/Engineering
Requires-Python: >=3.9
License-File: LICENSE
Requires-Dist: numpy
Requires-Dist: scipy
Requires-Dist: matplotlib
Requires-Dist: tqdm
Provides-Extra: dev
Requires-Dist: build ; extra == 'dev'
Requires-Dist: pre-commit ; extra == 'dev'
Provides-Extra: doc
Requires-Dist: sphinx ; extra == 'doc'
Requires-Dist: sphinx-rtd-theme ; extra == 'doc'
Requires-Dist: sphinx-argparse ; extra == 'doc'
